{
	"/:roomName/play": "/zonePlay",
	"/:roomName/pause": "/zonePause",
	"/:roomName/playpause": "/zonePlaypause",
	"/:roomName/volume/:volume": "/zoneVolume",
	"/:roomName/groupvolume/:volume": "/zoneGroupVolume",
	"/:roomName/mute": "/zoneMute",
	"/:roomName/unmute": "/zoneUnmute",
	"/:roomName/groupmute": "/zoneGroupMute",
	"/:roomName/togglemute": "/zoneTogglemute",
	"/:roomName/trackseek/:trackNumber": "/zoneTrackseek",
	"/:roomName/timeseek/:seconds": "/zoneTimeseek",
	"/:roomName/next": "/zoneNext",
	"/:roomName/previous": "/zonePrevious",
	"/:roomName/state": "/zoneState",
	"/:roomName/favorite": "/zoneFavorite",
	"/:roomName/favorites": "/zoneFavorites",
	"/:roomName/playlist": "/zonePlaylist",
	"/:roomName/repeat/:mode": "/zoneRepeat",
	"/:roomName/shuffle/:mode": "/zoneShuffle",
	"/:roomName/crossfade/:mode": "/zoneCrossfade",
	"/:roomName/say/:message": "/zoneSay",
	"/:roomName/queue": "/zoneQueue",
	"/:roomName/clearqueue": "/zoneClearqueue",
	"/:roomName/sleep": "/zoneSleep",
	"/:roomName/linein": "/zoneLinein",
	"/:roomName/clip": "/zoneClip",
	"/:roomName/join/:otherRoomName": "/zoneJoin",
	"/:roomName/leave": "/zoneLeave",
	"/:roomName/sub": "/zoneSub",
	"/:roomName/spotify/play/:trackId": "/zoneSpotifyPlay",
	"/:roomName/spotify/next/:trackId": "/zoneSpotifyNext",
	"/:roomName/spotify/queue/:trackId": "/zoneSpotifyQueue"
}
